furiosa/runtime/__init__.py
furiosa/runtime/_utils.py
furiosa/runtime/bench.py
furiosa/runtime/compiler.py
furiosa/runtime/envs.py
furiosa/runtime/errors.py
furiosa/runtime/git_version.txt
furiosa/runtime/model.py
furiosa/runtime/profiler.py
furiosa/runtime/py.typed
furiosa/runtime/session.py
furiosa/runtime/sync.py
furiosa/runtime/tensor.py
furiosa/runtime/legacy/_util.py
furiosa/runtime/legacy/compiler.py
furiosa/runtime/legacy/consts.py
furiosa/runtime/legacy/envs.py
furiosa/runtime/legacy/errors.py
furiosa/runtime/legacy/model.py
furiosa/runtime/legacy/profiler.py
furiosa/runtime/legacy/session.py
furiosa/runtime/legacy/tensor.py
furiosa/runtime/legacy/_api/__init__.py
furiosa/runtime/legacy/_api/v1.py
furiosa_runtime-0.10.2.dist-info/WHEEL
furiosa_runtime-0.10.2.dist-info/METADATA
furiosa_runtime-0.10.2.dist-info/RECORD
