Metadata-Version: 2.1
Name: furiosa-runtime
Version: 0.10.2
Summary: Provide high-level Python APIs to access Furiosa AI's NPUs and its eco-system
Author-email: "FurioaAI, Inc." <pkg@furiosa.ai>
Requires-Python: ~=3.8
Classifier: Development Status :: 4 - Beta
Classifier: Environment :: Console
Classifier: Intended Audience :: Developers
Classifier: Intended Audience :: System Administrators
Classifier: License :: OSI Approved :: Apache Software License
Classifier: Programming Language :: Python :: 3
Classifier: Programming Language :: Python :: 3.8
Classifier: Programming Language :: Python :: 3.9
Classifier: Programming Language :: Python :: 3.10
Classifier: Topic :: Software Development :: Libraries :: Python Modules
Classifier: Topic :: Scientific/Engineering :: Artificial Intelligence
Requires-Dist: furiosa-common == 0.10.*
Requires-Dist: furiosa-native-runtime == 0.10.*
Requires-Dist: cffi ~= 1.14
Requires-Dist: numpy ~= 1.24
Requires-Dist: pandas ~= 2.0.3
Requires-Dist: pydantic
Requires-Dist: package-extras ; extra == "legacy"
Requires-Dist: mnist ; extra == "test"
Requires-Dist: mypy ; extra == "test"
Requires-Dist: onnxruntime ~= 1.15.1 ; extra == "test"
Requires-Dist: pytest ; extra == "test"
Requires-Dist: ruff ; extra == "test"
Requires-Dist: types-PyYAML ; extra == "test"
Project-URL: Bug Tracker, https://github.com/furiosa-ai/furiosa-sdk/issues
Project-URL: Documentation, https://furiosa-ai.github.io/docs
Project-URL: Home, https://furiosa.ai
Project-URL: Source Code, https://github.com/furiosa-ai/furiosa-sdk
Provides-Extra: legacy
Provides-Extra: test
